fine_python_mypy/__init__.py
fine_python_mypy/action.py
fine_python_mypy/ast_provider.py
fine_python_mypy/iast_provider.py
fine_python_mypy/output_parser.py
fine_python_mypy/py.typed
fine_python_mypy-0.2.0.dist-info/METADATA
fine_python_mypy-0.2.0.dist-info/WHEEL
fine_python_mypy-0.2.0.dist-info/top_level.txt
fine_python_mypy-0.2.0.dist-info/RECORD
